PyxelApp/__init__.py
PyxelApp/pyxel_app.py
PyxelApp/template/entry.py
PyxelApp/template/pkg/__init__.py
PyxelApp/template/pkg/app.py
PyxelApp/template/pkg/utils.py
PyxelApp/template/pkg/data/img.pyxres
pyxel_app-0.1.1.dist-info/LICENSE
pyxel_app-0.1.1.dist-info/METADATA
pyxel_app-0.1.1.dist-info/WHEEL
pyxel_app-0.1.1.dist-info/entry_points.txt
pyxel_app-0.1.1.dist-info/top_level.txt
pyxel_app-0.1.1.dist-info/RECORD
