Metadata-Version: 2.1
Name: pyxel-app
Version: 0.1.1
Summary: Extension tool to create molds for pyxel applications with a single command
Home-page: https://github.com/n-koba0427/PyxelApp
Author: naoyashi
Author-email: n.koba0427@gmail.com
Classifier: License :: OSI Approved :: MIT License
Classifier: Programming Language :: Python
Classifier: Programming Language :: Python :: 3
Classifier: Programming Language :: Python :: 3.11
Classifier: Development Status :: 5 - Production/Stable
Classifier: Intended Audience :: Developers
Classifier: Natural Language :: Japanese
License-File: LICENSE
Requires-Dist: Click
Requires-Dist: pyxel-universal-font
